gocept.jslint-3.0-py3.7-nspkg.pth
gocept/jslint/__init__.py
gocept/jslint/case.py
gocept/jslint/util.py
gocept/jslint/tests/__init__.py
gocept/jslint/tests/test_case.py
gocept/jslint/tests/fixtures/one.js
gocept/jslint/tests/fixtures/predefined.js
gocept/jslint/tests/fixtures/two.js
gocept/jslint/tests/fixtures/second/one.js
gocept/jslint/tests/fixtures/third/one.js
gocept.jslint-3.0.dist-info/METADATA
gocept.jslint-3.0.dist-info/WHEEL
gocept.jslint-3.0.dist-info/entry_points.txt
gocept.jslint-3.0.dist-info/namespace_packages.txt
gocept.jslint-3.0.dist-info/top_level.txt
gocept.jslint-3.0.dist-info/RECORD
