Metadata-Version: 2.1
Name: gocept.jslint
Version: 3.0
Summary: Python-unittest integration for jslint.
Home-page: https://github.com/gocept/gocept.jslint
Author: Wolfgang Schnerring
Author-email: mail@gocept.com
License: ZPL
Platform: UNKNOWN
Classifier: Environment :: Web Environment
Classifier: Intended Audience :: Developers
Classifier: License :: OSI Approved :: Zope Public License
Classifier: License :: OSI Approved
Classifier: Natural Language :: English
Classifier: Operating System :: OS Independent
Classifier: Programming Language :: Python :: 3.6
Classifier: Programming Language :: Python :: 3.7
Classifier: Programming Language :: Python :: 3.8
Classifier: Programming Language :: Python :: 3.9
Classifier: Programming Language :: Python :: Implementation :: CPython
Classifier: Programming Language :: Python :: Implementation
Classifier: Programming Language :: Python
Classifier: Topic :: Software Development :: Testing
Classifier: Topic :: Software Development
Requires-Python: >=3.6, <4
Requires-Dist: setuptools
Provides-Extra: test
